setup.py
sunnyday/__init__.py
sunnyday/sunnyday.py
sunnyday_calcetto.egg-info/PKG-INFO
sunnyday_calcetto.egg-info/SOURCES.txt
sunnyday_calcetto.egg-info/dependency_links.txt
sunnyday_calcetto.egg-info/top_level.txt