Metadata-Version: 1.1
Name: sunnyday-calcetto
Version: 2.0.0
Summary: Weather forecast data
Home-page: https://github.com/denisvreshtazi/Weather-Package
Author: Denis Vreshtazi(helped by Ardit Sulce)
Author-email: vreshtazi21@gmail.com
License: MIT
Keywords: weather,forecast,openweather
Platform: UNKNOWN
Classifier: Development Status :: 3 - Alpha
Classifier: Intended Audience :: Developers
Classifier: License :: OSI Approved :: MIT License
Classifier: Programming Language :: Python :: 3
Classifier: Programming Language :: Python :: 3.7
Classifier: Programming Language :: Python :: 3.8
Classifier: Programming Language :: Python :: 3.9
Classifier: Programming Language :: Python :: 3.10
Classifier: Programming Language :: Python :: 3.11
Classifier: Topic :: Software Development :: Build Tools
